streamlit_cookies_controller/__init__.py
streamlit_cookies_controller/cookie_controller.py
streamlit_cookies_controller/utils.py
streamlit_cookies_controller/frontend/build/asset-manifest.json
streamlit_cookies_controller/frontend/build/index.html
streamlit_cookies_controller/frontend/build/static/js/main.ab7915bb.js
streamlit_cookies_controller/frontend/build/static/js/main.ab7915bb.js.LICENSE.txt
streamlit_cookies_controller/frontend/build/static/js/main.ab7915bb.js.map
streamlit_cookies_controller-0.0.4.dist-info/LICENSE
streamlit_cookies_controller-0.0.4.dist-info/METADATA
streamlit_cookies_controller-0.0.4.dist-info/WHEEL
streamlit_cookies_controller-0.0.4.dist-info/top_level.txt
streamlit_cookies_controller-0.0.4.dist-info/RECORD
